{
  "-10.0": {
    "-8.390625": {
      "-10.0": {
        "-7.43359375": 0
      },
      "-7.43359375": {
        "-5.48828125": 1
      },
      "-5.48828125": {
        "-4.0078125": 2
      },
      "-4.0078125": {
        "-2.86328125": 3
      },
      "-2.86328125": {
        "-1.9599609375": 4
      },
      "-1.9599609375": {
        "-1.2216796875": 5
      },
      "-1.2216796875": {
        "-0.58642578125": 6
      },
      "-0.58642578125": {
        "0.0": 7
      },
      "0.0": {
        "0.58642578125": 8
      },
      "0.58642578125": {
        "1.2216796875": 9
      },
      "1.2216796875": {
        "1.9599609375": 10
      },
      "1.9599609375": {
        "2.86328125": 11
      },
      "2.86328125": {
        "4.0078125": 12
      },
      "4.0078125": {
        "5.48828125": 13
      },
      "5.48828125": {
        "7.43359375": 14
      },
      "7.43359375": {
        "10.0": 15
      }
    }
  },
  "-8.390625": {
    "-6.96875": {
      "-10.0": {
        "-7.43359375": 16
      },
      "-7.43359375": {
        "-5.48828125": 17
      },
      "-5.48828125": {
        "-4.0078125": 18
      },
      "-4.0078125": {
        "-2.86328125": 19
      },
      "-2.86328125": {
        "-1.9599609375": 20
      },
      "-1.9599609375": {
        "-1.2216796875": 21
      },
      "-1.2216796875": {
        "-0.58642578125": 22
      },
      "-0.58642578125": {
        "0.0": 23
      },
      "0.0": {
        "0.58642578125": 24
      },
      "0.58642578125": {
        "1.2216796875": 25
      },
      "1.2216796875": {
        "1.9599609375": 26
      },
      "1.9599609375": {
        "2.86328125": 27
      },
      "2.86328125": {
        "4.0078125": 28
      },
      "4.0078125": {
        "5.48828125": 29
      },
      "5.48828125": {
        "7.43359375": 30
      },
      "7.43359375": {
        "10.0": 31
      }
    }
  },
  "-6.96875": {
    "-5.69140625": {
      "-10.0": {
        "-7.43359375": 32
      },
      "-7.43359375": {
        "-5.48828125": 33
      },
      "-5.48828125": {
        "-4.0078125": 34
      },
      "-4.0078125": {
        "-2.86328125": 35
      },
      "-2.86328125": {
        "-1.9599609375": 36
      },
      "-1.9599609375": {
        "-1.2216796875": 37
      },
      "-1.2216796875": {
        "-0.58642578125": 38
      },
      "-0.58642578125": {
        "0.0": 39
      },
      "0.0": {
        "0.58642578125": 40
      },
      "0.58642578125": {
        "1.2216796875": 41
      },
      "1.2216796875": {
        "1.9599609375": 42
      },
      "1.9599609375": {
        "2.86328125": 43
      },
      "2.86328125": {
        "4.0078125": 44
      },
      "4.0078125": {
        "5.48828125": 45
      },
      "5.48828125": {
        "7.43359375": 46
      },
      "7.43359375": {
        "10.0": 47
      }
    }
  },
  "-5.69140625": {
    "-4.53515625": {
      "-10.0": {
        "-7.43359375": 48
      },
      "-7.43359375": {
        "-5.48828125": 49
      },
      "-5.48828125": {
        "-4.0078125": 50
      },
      "-4.0078125": {
        "-2.86328125": 51
      },
      "-2.86328125": {
        "-1.9599609375": 52
      },
      "-1.9599609375": {
        "-1.2216796875": 53
      },
      "-1.2216796875": {
        "-0.58642578125": 54
      },
      "-0.58642578125": {
        "0.0": 55
      },
      "0.0": {
        "0.58642578125": 56
      },
      "0.58642578125": {
        "1.2216796875": 57
      },
      "1.2216796875": {
        "1.9599609375": 58
      },
      "1.9599609375": {
        "2.86328125": 59
      },
      "2.86328125": {
        "4.0078125": 60
      },
      "4.0078125": {
        "5.48828125": 61
      },
      "5.48828125": {
        "7.43359375": 62
      },
      "7.43359375": {
        "10.0": 63
      }
    }
  },
  "-4.53515625": {
    "-3.48046875": {
      "-10.0": {
        "-7.43359375": 64
      },
      "-7.43359375": {
        "-5.48828125": 65
      },
      "-5.48828125": {
        "-4.0078125": 66
      },
      "-4.0078125": {
        "-2.86328125": 67
      },
      "-2.86328125": {
        "-1.9599609375": 68
      },
      "-1.9599609375": {
        "-1.2216796875": 69
      },
      "-1.2216796875": {
        "-0.58642578125": 70
      },
      "-0.58642578125": {
        "0.0": 71
      },
      "0.0": {
        "0.58642578125": 72
      },
      "0.58642578125": {
        "1.2216796875": 73
      },
      "1.2216796875": {
        "1.9599609375": 74
      },
      "1.9599609375": {
        "2.86328125": 75
      },
      "2.86328125": {
        "4.0078125": 76
      },
      "4.0078125": {
        "5.48828125": 77
      },
      "5.48828125": {
        "7.43359375": 78
      },
      "7.43359375": {
        "10.0": 79
      }
    }
  },
  "-3.48046875": {
    "-2.498046875": {
      "-10.0": {
        "-7.43359375": 80
      },
      "-7.43359375": {
        "-5.48828125": 81
      },
      "-5.48828125": {
        "-4.0078125": 82
      },
      "-4.0078125": {
        "-2.86328125": 83
      },
      "-2.86328125": {
        "-1.9599609375": 84
      },
      "-1.9599609375": {
        "-1.2216796875": 85
      },
      "-1.2216796875": {
        "-0.58642578125": 86
      },
      "-0.58642578125": {
        "0.0": 87
      },
      "0.0": {
        "0.58642578125": 88
      },
      "0.58642578125": {
        "1.2216796875": 89
      },
      "1.2216796875": {
        "1.9599609375": 90
      },
      "1.9599609375": {
        "2.86328125": 91
      },
      "2.86328125": {
        "4.0078125": 92
      },
      "4.0078125": {
        "5.48828125": 93
      },
      "5.48828125": {
        "7.43359375": 94
      },
      "7.43359375": {
        "10.0": 95
      }
    }
  },
  "-2.498046875": {
    "-1.5693359375": {
      "-10.0": {
        "-7.43359375": 96
      },
      "-7.43359375": {
        "-5.48828125": 97
      },
      "-5.48828125": {
        "-4.0078125": 98
      },
      "-4.0078125": {
        "-2.86328125": 99
      },
      "-2.86328125": {
        "-1.9599609375": 100
      },
      "-1.9599609375": {
        "-1.2216796875": 101
      },
      "-1.2216796875": {
        "-0.58642578125": 102
      },
      "-0.58642578125": {
        "0.0": 103
      },
      "0.0": {
        "0.58642578125": 104
      },
      "0.58642578125": {
        "1.2216796875": 105
      },
      "1.2216796875": {
        "1.9599609375": 106
      },
      "1.9599609375": {
        "2.86328125": 107
      },
      "2.86328125": {
        "4.0078125": 108
      },
      "4.0078125": {
        "5.48828125": 109
      },
      "5.48828125": {
        "7.43359375": 110
      },
      "7.43359375": {
        "10.0": 111
      }
    }
  },
  "-1.5693359375": {
    "-0.6748046875": {
      "-10.0": {
        "-7.43359375": 112
      },
      "-7.43359375": {
        "-5.48828125": 113
      },
      "-5.48828125": {
        "-4.0078125": 114
      },
      "-4.0078125": {
        "-2.86328125": 115
      },
      "-2.86328125": {
        "-1.9599609375": 116
      },
      "-1.9599609375": {
        "-1.2216796875": 117
      },
      "-1.2216796875": {
        "-0.58642578125": 118
      },
      "-0.58642578125": {
        "0.0": 119
      },
      "0.0": {
        "0.58642578125": 120
      },
      "0.58642578125": {
        "1.2216796875": 121
      },
      "1.2216796875": {
        "1.9599609375": 122
      },
      "1.9599609375": {
        "2.86328125": 123
      },
      "2.86328125": {
        "4.0078125": 124
      },
      "4.0078125": {
        "5.48828125": 125
      },
      "5.48828125": {
        "7.43359375": 126
      },
      "7.43359375": {
        "10.0": 127
      }
    }
  },
  "-0.6748046875": {
    "0.205078125": {
      "-10.0": {
        "-7.43359375": 128
      },
      "-7.43359375": {
        "-5.48828125": 129
      },
      "-5.48828125": {
        "-4.0078125": 130
      },
      "-4.0078125": {
        "-2.86328125": 131
      },
      "-2.86328125": {
        "-1.9599609375": 132
      },
      "-1.9599609375": {
        "-1.2216796875": 133
      },
      "-1.2216796875": {
        "-0.58642578125": 134
      },
      "-0.58642578125": {
        "0.0": 135
      },
      "0.0": {
        "0.58642578125": 136
      },
      "0.58642578125": {
        "1.2216796875": 137
      },
      "1.2216796875": {
        "1.9599609375": 138
      },
      "1.9599609375": {
        "2.86328125": 139
      },
      "2.86328125": {
        "4.0078125": 140
      },
      "4.0078125": {
        "5.48828125": 141
      },
      "5.48828125": {
        "7.43359375": 142
      },
      "7.43359375": {
        "10.0": 143
      }
    }
  },
  "0.205078125": {
    "1.08984375": {
      "-10.0": {
        "-7.43359375": 144
      },
      "-7.43359375": {
        "-5.48828125": 145
      },
      "-5.48828125": {
        "-4.0078125": 146
      },
      "-4.0078125": {
        "-2.86328125": 147
      },
      "-2.86328125": {
        "-1.9599609375": 148
      },
      "-1.9599609375": {
        "-1.2216796875": 149
      },
      "-1.2216796875": {
        "-0.58642578125": 150
      },
      "-0.58642578125": {
        "0.0": 151
      },
      "0.0": {
        "0.58642578125": 152
      },
      "0.58642578125": {
        "1.2216796875": 153
      },
      "1.2216796875": {
        "1.9599609375": 154
      },
      "1.9599609375": {
        "2.86328125": 155
      },
      "2.86328125": {
        "4.0078125": 156
      },
      "4.0078125": {
        "5.48828125": 157
      },
      "5.48828125": {
        "7.43359375": 158
      },
      "7.43359375": {
        "10.0": 159
      }
    }
  },
  "1.08984375": {
    "1.9970703125": {
      "-10.0": {
        "-7.43359375": 160
      },
      "-7.43359375": {
        "-5.48828125": 161
      },
      "-5.48828125": {
        "-4.0078125": 162
      },
      "-4.0078125": {
        "-2.86328125": 163
      },
      "-2.86328125": {
        "-1.9599609375": 164
      },
      "-1.9599609375": {
        "-1.2216796875": 165
      },
      "-1.2216796875": {
        "-0.58642578125": 166
      },
      "-0.58642578125": {
        "0.0": 167
      },
      "0.0": {
        "0.58642578125": 168
      },
      "0.58642578125": {
        "1.2216796875": 169
      },
      "1.2216796875": {
        "1.9599609375": 170
      },
      "1.9599609375": {
        "2.86328125": 171
      },
      "2.86328125": {
        "4.0078125": 172
      },
      "4.0078125": {
        "5.48828125": 173
      },
      "5.48828125": {
        "7.43359375": 174
      },
      "7.43359375": {
        "10.0": 175
      }
    }
  },
  "1.9970703125": {
    "2.94921875": {
      "-10.0": {
        "-7.43359375": 176
      },
      "-7.43359375": {
        "-5.48828125": 177
      },
      "-5.48828125": {
        "-4.0078125": 178
      },
      "-4.0078125": {
        "-2.86328125": 179
      },
      "-2.86328125": {
        "-1.9599609375": 180
      },
      "-1.9599609375": {
        "-1.2216796875": 181
      },
      "-1.2216796875": {
        "-0.58642578125": 182
      },
      "-0.58642578125": {
        "0.0": 183
      },
      "0.0": {
        "0.58642578125": 184
      },
      "0.58642578125": {
        "1.2216796875": 185
      },
      "1.2216796875": {
        "1.9599609375": 186
      },
      "1.9599609375": {
        "2.86328125": 187
      },
      "2.86328125": {
        "4.0078125": 188
      },
      "4.0078125": {
        "5.48828125": 189
      },
      "5.48828125": {
        "7.43359375": 190
      },
      "7.43359375": {
        "10.0": 191
      }
    }
  },
  "2.94921875": {
    "3.962890625": {
      "-10.0": {
        "-7.43359375": 192
      },
      "-7.43359375": {
        "-5.48828125": 193
      },
      "-5.48828125": {
        "-4.0078125": 194
      },
      "-4.0078125": {
        "-2.86328125": 195
      },
      "-2.86328125": {
        "-1.9599609375": 196
      },
      "-1.9599609375": {
        "-1.2216796875": 197
      },
      "-1.2216796875": {
        "-0.58642578125": 198
      },
      "-0.58642578125": {
        "0.0": 199
      },
      "0.0": {
        "0.58642578125": 200
      },
      "0.58642578125": {
        "1.2216796875": 201
      },
      "1.2216796875": {
        "1.9599609375": 202
      },
      "1.9599609375": {
        "2.86328125": 203
      },
      "2.86328125": {
        "4.0078125": 204
      },
      "4.0078125": {
        "5.48828125": 205
      },
      "5.48828125": {
        "7.43359375": 206
      },
      "7.43359375": {
        "10.0": 207
      }
    }
  },
  "3.962890625": {
    "5.0625": {
      "-10.0": {
        "-7.43359375": 208
      },
      "-7.43359375": {
        "-5.48828125": 209
      },
      "-5.48828125": {
        "-4.0078125": 210
      },
      "-4.0078125": {
        "-2.86328125": 211
      },
      "-2.86328125": {
        "-1.9599609375": 212
      },
      "-1.9599609375": {
        "-1.2216796875": 213
      },
      "-1.2216796875": {
        "-0.58642578125": 214
      },
      "-0.58642578125": {
        "0.0": 215
      },
      "0.0": {
        "0.58642578125": 216
      },
      "0.58642578125": {
        "1.2216796875": 217
      },
      "1.2216796875": {
        "1.9599609375": 218
      },
      "1.9599609375": {
        "2.86328125": 219
      },
      "2.86328125": {
        "4.0078125": 220
      },
      "4.0078125": {
        "5.48828125": 221
      },
      "5.48828125": {
        "7.43359375": 222
      },
      "7.43359375": {
        "10.0": 223
      }
    }
  },
  "5.0625": {
    "6.26953125": {
      "-10.0": {
        "-7.43359375": 224
      },
      "-7.43359375": {
        "-5.48828125": 225
      },
      "-5.48828125": {
        "-4.0078125": 226
      },
      "-4.0078125": {
        "-2.86328125": 227
      },
      "-2.86328125": {
        "-1.9599609375": 228
      },
      "-1.9599609375": {
        "-1.2216796875": 229
      },
      "-1.2216796875": {
        "-0.58642578125": 230
      },
      "-0.58642578125": {
        "0.0": 231
      },
      "0.0": {
        "0.58642578125": 232
      },
      "0.58642578125": {
        "1.2216796875": 233
      },
      "1.2216796875": {
        "1.9599609375": 234
      },
      "1.9599609375": {
        "2.86328125": 235
      },
      "2.86328125": {
        "4.0078125": 236
      },
      "4.0078125": {
        "5.48828125": 237
      },
      "5.48828125": {
        "7.43359375": 238
      },
      "7.43359375": {
        "10.0": 239
      }
    }
  },
  "6.26953125": {
    "7.61328125": {
      "-10.0": {
        "-7.43359375": 240
      },
      "-7.43359375": {
        "-5.48828125": 241
      },
      "-5.48828125": {
        "-4.0078125": 242
      },
      "-4.0078125": {
        "-2.86328125": 243
      },
      "-2.86328125": {
        "-1.9599609375": 244
      },
      "-1.9599609375": {
        "-1.2216796875": 245
      },
      "-1.2216796875": {
        "-0.58642578125": 246
      },
      "-0.58642578125": {
        "0.0": 247
      },
      "0.0": {
        "0.58642578125": 248
      },
      "0.58642578125": {
        "1.2216796875": 249
      },
      "1.2216796875": {
        "1.9599609375": 250
      },
      "1.9599609375": {
        "2.86328125": 251
      },
      "2.86328125": {
        "4.0078125": 252
      },
      "4.0078125": {
        "5.48828125": 253
      },
      "5.48828125": {
        "7.43359375": 254
      },
      "7.43359375": {
        "10.0": 255
      }
    }
  },
  "7.61328125": {
    "9.1171875": {
      "-10.0": {
        "-7.43359375": 256
      },
      "-7.43359375": {
        "-5.48828125": 257
      },
      "-5.48828125": {
        "-4.0078125": 258
      },
      "-4.0078125": {
        "-2.86328125": 259
      },
      "-2.86328125": {
        "-1.9599609375": 260
      },
      "-1.9599609375": {
        "-1.2216796875": 261
      },
      "-1.2216796875": {
        "-0.58642578125": 262
      },
      "-0.58642578125": {
        "0.0": 263
      },
      "0.0": {
        "0.58642578125": 264
      },
      "0.58642578125": {
        "1.2216796875": 265
      },
      "1.2216796875": {
        "1.9599609375": 266
      },
      "1.9599609375": {
        "2.86328125": 267
      },
      "2.86328125": {
        "4.0078125": 268
      },
      "4.0078125": {
        "5.48828125": 269
      },
      "5.48828125": {
        "7.43359375": 270
      },
      "7.43359375": {
        "10.0": 271
      }
    }
  },
  "9.1171875": {
    "10.8203125": {
      "-10.0": {
        "-7.43359375": 272
      },
      "-7.43359375": {
        "-5.48828125": 273
      },
      "-5.48828125": {
        "-4.0078125": 274
      },
      "-4.0078125": {
        "-2.86328125": 275
      },
      "-2.86328125": {
        "-1.9599609375": 276
      },
      "-1.9599609375": {
        "-1.2216796875": 277
      },
      "-1.2216796875": {
        "-0.58642578125": 278
      },
      "-0.58642578125": {
        "0.0": 279
      },
      "0.0": {
        "0.58642578125": 280
      },
      "0.58642578125": {
        "1.2216796875": 281
      },
      "1.2216796875": {
        "1.9599609375": 282
      },
      "1.9599609375": {
        "2.86328125": 283
      },
      "2.86328125": {
        "4.0078125": 284
      },
      "4.0078125": {
        "5.48828125": 285
      },
      "5.48828125": {
        "7.43359375": 286
      },
      "7.43359375": {
        "10.0": 287
      }
    }
  },
  "10.8203125": {
    "12.7578125": {
      "-10.0": {
        "-7.43359375": 288
      },
      "-7.43359375": {
        "-5.48828125": 289
      },
      "-5.48828125": {
        "-4.0078125": 290
      },
      "-4.0078125": {
        "-2.86328125": 291
      },
      "-2.86328125": {
        "-1.9599609375": 292
      },
      "-1.9599609375": {
        "-1.2216796875": 293
      },
      "-1.2216796875": {
        "-0.58642578125": 294
      },
      "-0.58642578125": {
        "0.0": 295
      },
      "0.0": {
        "0.58642578125": 296
      },
      "0.58642578125": {
        "1.2216796875": 297
      },
      "1.2216796875": {
        "1.9599609375": 298
      },
      "1.9599609375": {
        "2.86328125": 299
      },
      "2.86328125": {
        "4.0078125": 300
      },
      "4.0078125": {
        "5.48828125": 301
      },
      "5.48828125": {
        "7.43359375": 302
      },
      "7.43359375": {
        "10.0": 303
      }
    }
  },
  "12.7578125": {
    "14.9609375": {
      "-10.0": {
        "-7.43359375": 304
      },
      "-7.43359375": {
        "-5.48828125": 305
      },
      "-5.48828125": {
        "-4.0078125": 306
      },
      "-4.0078125": {
        "-2.86328125": 307
      },
      "-2.86328125": {
        "-1.9599609375": 308
      },
      "-1.9599609375": {
        "-1.2216796875": 309
      },
      "-1.2216796875": {
        "-0.58642578125": 310
      },
      "-0.58642578125": {
        "0.0": 311
      },
      "0.0": {
        "0.58642578125": 312
      },
      "0.58642578125": {
        "1.2216796875": 313
      },
      "1.2216796875": {
        "1.9599609375": 314
      },
      "1.9599609375": {
        "2.86328125": 315
      },
      "2.86328125": {
        "4.0078125": 316
      },
      "4.0078125": {
        "5.48828125": 317
      },
      "5.48828125": {
        "7.43359375": 318
      },
      "7.43359375": {
        "10.0": 319
      }
    }
  },
  "14.9609375": {
    "17.5": {
      "-10.0": {
        "-7.43359375": 320
      },
      "-7.43359375": {
        "-5.48828125": 321
      },
      "-5.48828125": {
        "-4.0078125": 322
      },
      "-4.0078125": {
        "-2.86328125": 323
      },
      "-2.86328125": {
        "-1.9599609375": 324
      },
      "-1.9599609375": {
        "-1.2216796875": 325
      },
      "-1.2216796875": {
        "-0.58642578125": 326
      },
      "-0.58642578125": {
        "0.0": 327
      },
      "0.0": {
        "0.58642578125": 328
      },
      "0.58642578125": {
        "1.2216796875": 329
      },
      "1.2216796875": {
        "1.9599609375": 330
      },
      "1.9599609375": {
        "2.86328125": 331
      },
      "2.86328125": {
        "4.0078125": 332
      },
      "4.0078125": {
        "5.48828125": 333
      },
      "5.48828125": {
        "7.43359375": 334
      },
      "7.43359375": {
        "10.0": 335
      }
    }
  },
  "17.5": {
    "20.40625": {
      "-10.0": {
        "-7.43359375": 336
      },
      "-7.43359375": {
        "-5.48828125": 337
      },
      "-5.48828125": {
        "-4.0078125": 338
      },
      "-4.0078125": {
        "-2.86328125": 339
      },
      "-2.86328125": {
        "-1.9599609375": 340
      },
      "-1.9599609375": {
        "-1.2216796875": 341
      },
      "-1.2216796875": {
        "-0.58642578125": 342
      },
      "-0.58642578125": {
        "0.0": 343
      },
      "0.0": {
        "0.58642578125": 344
      },
      "0.58642578125": {
        "1.2216796875": 345
      },
      "1.2216796875": {
        "1.9599609375": 346
      },
      "1.9599609375": {
        "2.86328125": 347
      },
      "2.86328125": {
        "4.0078125": 348
      },
      "4.0078125": {
        "5.48828125": 349
      },
      "5.48828125": {
        "7.43359375": 350
      },
      "7.43359375": {
        "10.0": 351
      }
    }
  },
  "20.40625": {
    "23.75": {
      "-10.0": {
        "-7.43359375": 352
      },
      "-7.43359375": {
        "-5.48828125": 353
      },
      "-5.48828125": {
        "-4.0078125": 354
      },
      "-4.0078125": {
        "-2.86328125": 355
      },
      "-2.86328125": {
        "-1.9599609375": 356
      },
      "-1.9599609375": {
        "-1.2216796875": 357
      },
      "-1.2216796875": {
        "-0.58642578125": 358
      },
      "-0.58642578125": {
        "0.0": 359
      },
      "0.0": {
        "0.58642578125": 360
      },
      "0.58642578125": {
        "1.2216796875": 361
      },
      "1.2216796875": {
        "1.9599609375": 362
      },
      "1.9599609375": {
        "2.86328125": 363
      },
      "2.86328125": {
        "4.0078125": 364
      },
      "4.0078125": {
        "5.48828125": 365
      },
      "5.48828125": {
        "7.43359375": 366
      },
      "7.43359375": {
        "10.0": 367
      }
    }
  },
  "23.75": {
    "27.59375": {
      "-10.0": {
        "-7.43359375": 368
      },
      "-7.43359375": {
        "-5.48828125": 369
      },
      "-5.48828125": {
        "-4.0078125": 370
      },
      "-4.0078125": {
        "-2.86328125": 371
      },
      "-2.86328125": {
        "-1.9599609375": 372
      },
      "-1.9599609375": {
        "-1.2216796875": 373
      },
      "-1.2216796875": {
        "-0.58642578125": 374
      },
      "-0.58642578125": {
        "0.0": 375
      },
      "0.0": {
        "0.58642578125": 376
      },
      "0.58642578125": {
        "1.2216796875": 377
      },
      "1.2216796875": {
        "1.9599609375": 378
      },
      "1.9599609375": {
        "2.86328125": 379
      },
      "2.86328125": {
        "4.0078125": 380
      },
      "4.0078125": {
        "5.48828125": 381
      },
      "5.48828125": {
        "7.43359375": 382
      },
      "7.43359375": {
        "10.0": 383
      }
    }
  },
  "27.59375": {
    "32.03125": {
      "-10.0": {
        "-7.43359375": 384
      },
      "-7.43359375": {
        "-5.48828125": 385
      },
      "-5.48828125": {
        "-4.0078125": 386
      },
      "-4.0078125": {
        "-2.86328125": 387
      },
      "-2.86328125": {
        "-1.9599609375": 388
      },
      "-1.9599609375": {
        "-1.2216796875": 389
      },
      "-1.2216796875": {
        "-0.58642578125": 390
      },
      "-0.58642578125": {
        "0.0": 391
      },
      "0.0": {
        "0.58642578125": 392
      },
      "0.58642578125": {
        "1.2216796875": 393
      },
      "1.2216796875": {
        "1.9599609375": 394
      },
      "1.9599609375": {
        "2.86328125": 395
      },
      "2.86328125": {
        "4.0078125": 396
      },
      "4.0078125": {
        "5.48828125": 397
      },
      "5.48828125": {
        "7.43359375": 398
      },
      "7.43359375": {
        "10.0": 399
      }
    }
  },
  "32.03125": {
    "37.1875": {
      "-10.0": {
        "-7.43359375": 400
      },
      "-7.43359375": {
        "-5.48828125": 401
      },
      "-5.48828125": {
        "-4.0078125": 402
      },
      "-4.0078125": {
        "-2.86328125": 403
      },
      "-2.86328125": {
        "-1.9599609375": 404
      },
      "-1.9599609375": {
        "-1.2216796875": 405
      },
      "-1.2216796875": {
        "-0.58642578125": 406
      },
      "-0.58642578125": {
        "0.0": 407
      },
      "0.0": {
        "0.58642578125": 408
      },
      "0.58642578125": {
        "1.2216796875": 409
      },
      "1.2216796875": {
        "1.9599609375": 410
      },
      "1.9599609375": {
        "2.86328125": 411
      },
      "2.86328125": {
        "4.0078125": 412
      },
      "4.0078125": {
        "5.48828125": 413
      },
      "5.48828125": {
        "7.43359375": 414
      },
      "7.43359375": {
        "10.0": 415
      }
    }
  },
  "37.1875": {
    "43.125": {
      "-10.0": {
        "-7.43359375": 416
      },
      "-7.43359375": {
        "-5.48828125": 417
      },
      "-5.48828125": {
        "-4.0078125": 418
      },
      "-4.0078125": {
        "-2.86328125": 419
      },
      "-2.86328125": {
        "-1.9599609375": 420
      },
      "-1.9599609375": {
        "-1.2216796875": 421
      },
      "-1.2216796875": {
        "-0.58642578125": 422
      },
      "-0.58642578125": {
        "0.0": 423
      },
      "0.0": {
        "0.58642578125": 424
      },
      "0.58642578125": {
        "1.2216796875": 425
      },
      "1.2216796875": {
        "1.9599609375": 426
      },
      "1.9599609375": {
        "2.86328125": 427
      },
      "2.86328125": {
        "4.0078125": 428
      },
      "4.0078125": {
        "5.48828125": 429
      },
      "5.48828125": {
        "7.43359375": 430
      },
      "7.43359375": {
        "10.0": 431
      }
    }
  },
  "43.125": {
    "49.96875": {
      "-10.0": {
        "-7.43359375": 432
      },
      "-7.43359375": {
        "-5.48828125": 433
      },
      "-5.48828125": {
        "-4.0078125": 434
      },
      "-4.0078125": {
        "-2.86328125": 435
      },
      "-2.86328125": {
        "-1.9599609375": 436
      },
      "-1.9599609375": {
        "-1.2216796875": 437
      },
      "-1.2216796875": {
        "-0.58642578125": 438
      },
      "-0.58642578125": {
        "0.0": 439
      },
      "0.0": {
        "0.58642578125": 440
      },
      "0.58642578125": {
        "1.2216796875": 441
      },
      "1.2216796875": {
        "1.9599609375": 442
      },
      "1.9599609375": {
        "2.86328125": 443
      },
      "2.86328125": {
        "4.0078125": 444
      },
      "4.0078125": {
        "5.48828125": 445
      },
      "5.48828125": {
        "7.43359375": 446
      },
      "7.43359375": {
        "10.0": 447
      }
    }
  },
  "49.96875": {
    "57.90625": {
      "-10.0": {
        "-7.43359375": 448
      },
      "-7.43359375": {
        "-5.48828125": 449
      },
      "-5.48828125": {
        "-4.0078125": 450
      },
      "-4.0078125": {
        "-2.86328125": 451
      },
      "-2.86328125": {
        "-1.9599609375": 452
      },
      "-1.9599609375": {
        "-1.2216796875": 453
      },
      "-1.2216796875": {
        "-0.58642578125": 454
      },
      "-0.58642578125": {
        "0.0": 455
      },
      "0.0": {
        "0.58642578125": 456
      },
      "0.58642578125": {
        "1.2216796875": 457
      },
      "1.2216796875": {
        "1.9599609375": 458
      },
      "1.9599609375": {
        "2.86328125": 459
      },
      "2.86328125": {
        "4.0078125": 460
      },
      "4.0078125": {
        "5.48828125": 461
      },
      "5.48828125": {
        "7.43359375": 462
      },
      "7.43359375": {
        "10.0": 463
      }
    }
  },
  "57.90625": {
    "67.0625": {
      "-10.0": {
        "-7.43359375": 464
      },
      "-7.43359375": {
        "-5.48828125": 465
      },
      "-5.48828125": {
        "-4.0078125": 466
      },
      "-4.0078125": {
        "-2.86328125": 467
      },
      "-2.86328125": {
        "-1.9599609375": 468
      },
      "-1.9599609375": {
        "-1.2216796875": 469
      },
      "-1.2216796875": {
        "-0.58642578125": 470
      },
      "-0.58642578125": {
        "0.0": 471
      },
      "0.0": {
        "0.58642578125": 472
      },
      "0.58642578125": {
        "1.2216796875": 473
      },
      "1.2216796875": {
        "1.9599609375": 474
      },
      "1.9599609375": {
        "2.86328125": 475
      },
      "2.86328125": {
        "4.0078125": 476
      },
      "4.0078125": {
        "5.48828125": 477
      },
      "5.48828125": {
        "7.43359375": 478
      },
      "7.43359375": {
        "10.0": 479
      }
    }
  },
  "67.0625": {
    "77.6875": {
      "-10.0": {
        "-7.43359375": 480
      },
      "-7.43359375": {
        "-5.48828125": 481
      },
      "-5.48828125": {
        "-4.0078125": 482
      },
      "-4.0078125": {
        "-2.86328125": 483
      },
      "-2.86328125": {
        "-1.9599609375": 484
      },
      "-1.9599609375": {
        "-1.2216796875": 485
      },
      "-1.2216796875": {
        "-0.58642578125": 486
      },
      "-0.58642578125": {
        "0.0": 487
      },
      "0.0": {
        "0.58642578125": 488
      },
      "0.58642578125": {
        "1.2216796875": 489
      },
      "1.2216796875": {
        "1.9599609375": 490
      },
      "1.9599609375": {
        "2.86328125": 491
      },
      "2.86328125": {
        "4.0078125": 492
      },
      "4.0078125": {
        "5.48828125": 493
      },
      "5.48828125": {
        "7.43359375": 494
      },
      "7.43359375": {
        "10.0": 495
      }
    }
  },
  "77.6875": {
    "90.0": {
      "-10.0": {
        "-7.43359375": 496
      },
      "-7.43359375": {
        "-5.48828125": 497
      },
      "-5.48828125": {
        "-4.0078125": 498
      },
      "-4.0078125": {
        "-2.86328125": 499
      },
      "-2.86328125": {
        "-1.9599609375": 500
      },
      "-1.9599609375": {
        "-1.2216796875": 501
      },
      "-1.2216796875": {
        "-0.58642578125": 502
      },
      "-0.58642578125": {
        "0.0": 503
      },
      "0.0": {
        "0.58642578125": 504
      },
      "0.58642578125": {
        "1.2216796875": 505
      },
      "1.2216796875": {
        "1.9599609375": 506
      },
      "1.9599609375": {
        "2.86328125": 507
      },
      "2.86328125": {
        "4.0078125": 508
      },
      "4.0078125": {
        "5.48828125": 509
      },
      "5.48828125": {
        "7.43359375": 510
      },
      "7.43359375": {
        "10.0": 511
      }
    }
  }
}